geosynth/__init__.py
geosynth/__main__.py
geosynth/_download.py
geosynth/_plt_to_numpy.py
geosynth/_visualize_instances.py
geosynth/cli/__init__.py
geosynth/cli/download.py
geosynth/cli/main.py
geosynth/common.py
geosynth/data.py
geosynth/dataset.py
geosynth/helpers.py
geosynth/mappings/__init__.py
geosynth/mappings/_turbo.py
geosynth/mappings/semantic.py
geosynth/mappings/utils.py
geosynth/models/lighting.py
geosynth/progress.py
geosynth/py.typed
geosynth/scene.py
geosynth-1.0.1.dist-info/LICENSE
geosynth-1.0.1.dist-info/METADATA
geosynth-1.0.1.dist-info/WHEEL
geosynth-1.0.1.dist-info/entry_points.txt
geosynth-1.0.1.dist-info/RECORD
