Metadata-Version: 2.1
Name: geosynth
Version: 1.0.1
Summary: 
Home-page: https://github.com/geomagical/geosynth
License: Apache-2.0
Author: Geomagical Labs
Requires-Python: >=3.8,<4.0
Classifier: License :: OSI Approved :: Apache Software License
Classifier: Programming Language :: Python :: 3
Classifier: Programming Language :: Python :: 3.8
Classifier: Programming Language :: Python :: 3.9
Classifier: Programming Language :: Python :: 3.10
Classifier: Programming Language :: Python :: 3.11
Classifier: Programming Language :: Python :: 3.12
Requires-Dist: autoregistry (>=1.0.0)
Requires-Dist: numpy (>=1.19,<2.0)
Requires-Dist: opencv-python-headless (>=4.4,<5.0)
Requires-Dist: pydantic (>=1.8,<2.0)
Requires-Dist: rich (>=11.2.0)
Requires-Dist: typer (>=0.7.0)
Project-URL: Repository, https://github.com/geomagical/geosynth
